{"v":"5.5.2","meta":{"a":"SVGator","d":"SVGator, the ultimate SVG animation generator now supports Lottie: a thoughtfully designed, intuitive interface, right at your fingertips.","g":"Made in SVGator (https://www.svgator.com/)","tc":""},"metadata":{"filename":"working_girl.json","customProps":{"k":["SVGator","svgator","lottie animation","svg animation","lottie","svg"],"version":1,"app":"https://app.svgator.com/","site":"https://www.svgator.com/","date":"2024-06-11T03:35:51.655Z"}},"nm":"working_girl","ddd":0,"assets":[],"w":758,"h":437,"ip":0,"op":300,"fr":100,"fonts":{"list":[]},"layers":[{"ty":4,"st":0,"ip":0,"op":300,"ks":{"a":{"a":0,"k":[231.534081,343.003601]},"p":{"a":0,"k":[276.713469,343.003601]},"s":{"a":0,"k":[100,100]},"r":{"a":0,"k":0},"o":{"a":0,"k":100},"sk":{"a":0,"k":0},"sa":{"a":0,"k":0}},"shapes":[{"ty":"sh","ks":{"a":0,"k":{"v":[[332.477,426.801],[130.592,426.801],[129.895,426.104],[130.592,425.406],[331.43,425.406],[262.597,260.17],[262.973,259.258],[263.886,259.634],[333.121,425.836],[333.056,426.492],[332.477,426.801]],"i":[[0,0],[0,0],[0,0.385],[-0.385,0],[0,0],[0,0],[-0.356,0.148],[-0.148,-0.357],[0,0],[0.13,-0.194],[0.233,0]],"o":[[0,0],[-0.385,0],[0,-0.385],[0,0],[0,0],[-0.147,-0.356],[0.352,-0.143],[0,0],[0.087,0.215],[-0.129,0.194],[0,0]],"c":false}},"hd":false,"bm":0,"ln":""},{"ty":"fl","o":{"a":0,"k":100},"c":{"a":0,"k":[0.94902,0.913725,0.854902]},"hd":false,"bm":0,"ln":"","r":1}],"hd":false,"bm":0,"ln":"","ao":0,"hasMask":false,"tt":0,"td":0},{"ty":4,"st":0,"ip":0,"op":300,"ks":{"a":{"a":0,"k":[201.642448,339.997002]},"p":{"a":0,"k":[246.821836,339.299385]},"s":{"a":0,"k":[100,101.6196]},"r":{"a":0,"k":0},"o":{"a":0,"k":100},"sk":{"a":0,"k":0},"sa":{"a":0,"k":0}},"shapes":[{"ty":"sh","ks":{"a":0,"k":{"v":[[129.197,426.104],[343.85,426.104],[274.088,253.89],[59.4349,253.89],[129.197,426.104]],"i":[[0,0],[0,0],[0,0],[0,0],[0,0]],"o":[[0,0],[0,0],[0,0],[0,0],[0,0]],"c":false}},"hd":false,"bm":0,"ln":""},{"ty":"fl","o":{"a":0,"k":100},"c":{"a":0,"k":[0.058824,0.298039,0.458824]},"hd":false,"bm":0,"ln":"","r":1}],"hd":false,"bm":0,"ln":"","ao":0,"hasMask":false,"tt":0,"td":0},{"ty":4,"st":0,"ip":0,"op":300,"ks":{"a":{"a":0,"k":[285.66951,431.533997]},"p":{"a":0,"k":[329.996046,431.533997]},"s":{"a":0,"k":[100,100]},"r":{"a":0,"k":0},"o":{"a":0,"k":100},"sk":{"a":0,"k":0},"sa":{"a":0,"k":0}},"shapes":[{"ty":"sh","ks":{"a":0,"k":{"v":[[442.142,426.104],[129.197,426.104],[129.197,436.964],[442.142,436.964],[442.142,426.104]],"i":[[0,0],[0,0],[0,0],[0,0],[0,0]],"o":[[0,0],[0,0],[0,0],[0,0],[0,0]],"c":false}},"hd":false,"bm":0,"ln":""},{"ty":"fl","o":{"a":0,"k":100},"c":{"a":0,"k":[0.058824,0.298039,0.458824]},"hd":false,"bm":0,"ln":"","r":1}],"hd":false,"bm":0,"ln":"","ao":0,"hasMask":false,"tt":0,"td":0},{"ty":4,"st":0,"ip":0,"op":300,"ks":{"a":{"a":0,"k":[450.733414,487.883535]},"p":{"a":1,"k":[{"t":0,"s":[440.15643,402.209628],"i":{"x":1,"y":1},"o":{"x":0,"y":0},"h":0,"ti":[0,0],"to":[0,0]},{"t":50,"s":[439.971066,403.825981],"i":{"x":1,"y":1},"o":{"x":0,"y":0},"h":0,"ti":[0,0],"to":[0,0]},{"t":100,"s":[440.15643,401.209628],"i":{"x":1,"y":1},"o":{"x":0,"y":0},"h":0,"ti":[0,0],"to":[0,0]},{"t":150,"s":[439.971066,403.825981],"i":{"x":1,"y":1},"o":{"x":0,"y":0},"h":0,"ti":[0,0],"to":[0,0]},{"t":200,"s":[440.15643,401.209628],"i":{"x":1,"y":1},"o":{"x":0,"y":0},"h":0,"ti":[0,0],"to":[0,0]},{"t":250,"s":[439.971066,403.825981],"i":{"x":1,"y":1},"o":{"x":0,"y":0},"h":0,"ti":[0,0],"to":[0,0]},{"t":300,"s":[440.15643,401.209628],"i":{"x":1,"y":1},"o":{"x":0,"y":0},"h":0,"ti":[0,0],"to":[0,0]}]},"s":{"a":0,"k":[100,100]},"r":{"a":0,"k":7.242158},"o":{"a":0,"k":100},"sk":{"a":0,"k":0},"sa":{"a":0,"k":0}},"shapes":[{"ty":"sh","ks":{"a":0,"k":{"v":[[394.093665,519.885154],[388.107564,485.184341],[432.966,459.088117],[521.732647,457.12658],[524.469873,503.317339],[460.778855,508.381552],[423.366063,519.749745],[457.263847,488.005432],[427.338674,499.874943],[418.3309,520.618341],[413.992654,495.469977],[446.595655,475.094789],[412.111852,495.708984],[400.107184,518.847785],[395.436091,491.769944],[427.931874,469.0465],[394.093665,519.885154]],"i":[[0,0],[-1.240255,11.586937],[-23.626411,5.409409],[-25.039541,-7.855539],[0,0],[16.58078,3.442505],[11.151267,3.519838],[-20.8728,8.065638],[19.653743,-3.39039],[-0.000001,-0.000001],[-6.119719,23.511533],[-10.725248,0.287416],[0,0.000001],[6.267723,8.386008],[-1.319172,11.593671],[-16.886295,4.799946],[15.686281,-2.705977]],"o":[[-7.540662,-4.746382],[4.027461,-12.550329],[28.137183,-5.188235],[0,0],[-17.107797,4.979291],[-9.260936,0.646112],[-10.169374,-3.159979],[8.640601,-3.338889],[-0.34192,12.061874],[-7.159326,4.926935],[-0.002485,-11.610575],[-34.902066,9.873409],[-1.880299,21.449688],[0,0.000001],[3.26639,-8.746777],[-54.928357,14.821807],[0,0]],"c":false}},"hd":false,"bm":0,"ln":""},{"ty":"st","o":{"a":0,"k":100},"w":{"a":0,"k":1.516},"c":{"a":0,"k":[0.145098,0.160784,0.168627]},"hd":false,"bm":0,"ln":"","lc":1,"lj":1,"ml":4,"ml2":{"a":0,"k":0},"d":[{"n":"o","nm":"offset","v":{"a":0,"k":0}}]},{"ty":"fl","o":{"a":0,"k":100},"c":{"a":0,"k":[0.94902,0.913725,0.854902]},"hd":false,"bm":0,"ln":"","r":1}],"hd":false,"bm":0,"ln":"","ao":0,"hasMask":false,"tt":0,"td":0},{"ty":4,"st":0,"ip":0,"op":300,"ks":{"a":{"a":0,"k":[536.522491,403.817444]},"p":{"a":0,"k":[536.522491,404.817444]},"s":{"a":0,"k":[100,100]},"r":{"a":0,"k":0},"o":{"a":0,"k":100},"sk":{"a":0,"k":0},"sa":{"a":0,"k":0}},"shapes":[{"ty":"sh","ks":{"a":0,"k":{"v":[[531.223,433.329],[531.094,433.318],[530.535,432.505],[541.137,374.874],[541.951,374.315],[542.51,375.128],[531.908,432.759],[531.223,433.329]],"i":[[0,0],[0.044,0.007],[-0.07,0.378],[0,0],[-0.39,-0.06],[0.07,-0.378],[0,0],[0.329,0]],"o":[[-0.042,0],[-0.378,-0.071],[0,0],[0.071,-0.378],[0.378,0.071],[0,0],[-0.063,0.336],[0,0]],"c":false}},"hd":false,"bm":0,"ln":""},{"ty":"fl","o":{"a":0,"k":100},"c":{"a":0,"k":[0.145098,0.160784,0.168627]},"hd":false,"bm":0,"ln":"","r":1}],"hd":false,"bm":0,"ln":"","ao":0,"hasMask":false,"tt":0,"td":0},{"ty":4,"st":0,"ip":0,"op":300,"ks":{"a":{"a":0,"k":[560.311691,347.271042]},"p":{"a":0,"k":[560.311691,348.271042]},"s":{"a":0,"k":[100,100]},"r":{"a":0,"k":0},"o":{"a":0,"k":100},"sk":{"a":0,"k":0},"sa":{"a":0,"k":0}},"shapes":[{"ty":"sh","ks":{"a":0,"k":{"v":[[510.667,435.335],[510.614,435.333],[509.969,434.585],[514.459,374.318],[515.101,373.674],[609.157,366.319],[592.979,260.008],[593.564,259.214],[594.358,259.799],[610.648,366.852],[610.505,367.39],[610.012,367.653],[515.804,375.021],[511.359,434.693],[510.667,435.335]],"i":[[0,0],[0.018,0.002],[-0.028,0.384],[0,0],[-0.343,0.027],[0,0],[0,0],[-0.381,0.057],[-0.058,-0.381],[0,0],[0.12,-0.152],[0.194,-0.016],[0,0],[0,0],[0.36,0]],"o":[[-0.018,0],[-0.384,-0.029],[0,0],[0.026,-0.344],[0,0],[0,0],[-0.059,-0.381],[0.381,-0.053],[0,0],[0.03,0.192],[-0.12,0.152],[0,0],[0,0],[-0.025,0.362],[0,0]],"c":false}},"hd":false,"bm":0,"ln":""},{"ty":"fl","o":{"a":0,"k":100},"c":{"a":0,"k":[0.145098,0.160784,0.168627]},"hd":false,"bm":0,"ln":"","r":1}],"hd":false,"bm":0,"ln":"","ao":0,"hasMask":false,"tt":0,"td":0},{"ty":4,"st":0,"ip":0,"op":300,"ks":{"a":{"a":0,"k":[438.065628,277.516083]},"p":{"a":0,"k":[438.065628,278.516083]},"s":{"a":0,"k":[100,100]},"r":{"a":0,"k":0},"o":{"a":0,"k":100},"sk":{"a":0,"k":0},"sa":{"a":0,"k":0}},"shapes":[{"ty":"sh","ks":{"a":0,"k":{"v":[[448.921,367.651],[448.26,367.177],[426.575,259.922],[446.41,187.626],[447.394,187.546],[447.473,188.53],[427.97,259.881],[449.581,366.73],[449.145,367.615],[448.921,367.651]],"i":[[0,0],[0.099,0.291],[1.345,46.69],[-0.212,0.248],[-0.295,-0.248],[0.249,-0.295],[-1.332,-46.28],[-0.202,-0.598],[0.364,-0.124],[0.073,0]],"o":[[-0.291,0],[-0.204,-0.6],[-1.349,-46.851],[0.248,-0.292],[0.293,0.25],[-0.208,0.245],[1.338,46.48],[0.125,0.366],[-0.074,0.024],[0,0]],"c":false}},"hd":false,"bm":0,"ln":""},{"ty":"fl","o":{"a":0,"k":100},"c":{"a":0,"k":[0.145098,0.160784,0.168627]},"hd":false,"bm":0,"ln":"","r":1}],"hd":false,"bm":0,"ln":"","ao":0,"hasMask":false,"tt":0,"td":0},{"ty":4,"st":0,"ip":0,"op":300,"ks":{"a":{"a":0,"k":[543.440186,272.04937]},"p":{"a":0,"k":[543.440186,273.04937]},"s":{"a":0,"k":[100,100]},"r":{"a":0,"k":0},"o":{"a":0,"k":100},"sk":{"a":0,"k":0},"sa":{"a":0,"k":0}},"shapes":[{"ty":"sh","ks":{"a":0,"k":{"v":[[523.852,370.366],[523.578,370.311],[523.21,369.395],[562.33,240.893],[541.94,174.838],[542.099,173.864],[543.073,174.023],[563.725,240.902],[524.494,369.942],[523.852,370.366]],"i":[[0,0],[0.088,0.037],[-0.151,0.355],[-0.193,37.052],[0.205,0.286],[-0.311,0.225],[-0.226,-0.314],[0.191,-37.419],[0.389,-0.912],[0.27,0]],"o":[[-0.091,0],[-0.354,-0.151],[0.389,-0.909],[0.19,-36.95],[-0.225,-0.314],[0.314,-0.224],[0.207,0.291],[-0.194,37.331],[-0.113,0.265],[0,0]],"c":false}},"hd":false,"bm":0,"ln":""},{"ty":"fl","o":{"a":0,"k":100},"c":{"a":0,"k":[0.145098,0.160784,0.168627]},"hd":false,"bm":0,"ln":"","r":1}],"hd":false,"bm":0,"ln":"","ao":0,"hasMask":false,"tt":0,"td":0},{"ty":4,"st":0,"ip":0,"op":300,"ks":{"a":{"a":0,"k":[414.777893,344.263641]},"p":{"a":0,"k":[414.777893,345.263641]},"s":{"a":0,"k":[100,100]},"r":{"a":0,"k":0},"o":{"a":0,"k":100},"sk":{"a":0,"k":0},"sa":{"a":0,"k":0}},"shapes":[{"ty":"sh","ks":{"a":0,"k":{"v":[[426.496,435.335],[425.802,434.704],[419.596,369.9],[402.534,330.979],[419.607,253.683],[420.481,253.224],[420.94,254.098],[403.915,330.786],[420.862,369.295],[420.968,369.603],[427.19,434.571],[426.563,435.333],[426.496,435.335]],"i":[[0,0],[0.035,0.361],[0,0],[2.067,14.842],[-0.784,2.523],[-0.373,-0.115],[0.114,-0.368],[-2.087,-14.99],[-0.148,-0.233],[-0.011,-0.109],[0,0],[0.382,-0.036],[0.023,0]],"o":[[-0.355,0],[0,0],[-1.364,-2.162],[-2.131,-15.301],[0.113,-0.366],[0.368,0.115],[-0.193,0.615],[2.089,14.993],[0.058,0.092],[0,0],[0.037,0.384],[-0.021,0],[0,0]],"c":false}},"hd":false,"bm":0,"ln":""},{"ty":"fl","o":{"a":0,"k":100},"c":{"a":0,"k":[0.145098,0.160784,0.168627]},"hd":false,"bm":0,"ln":"","r":1}],"hd":false,"bm":0,"ln":"","ao":0,"hasMask":false,"tt":0,"td":0},{"ty":4,"st":0,"ip":0,"op":300,"ks":{"a":{"a":0,"k":[493.478577,202.208992]},"p":{"a":0,"k":[493.478577,203.208992]},"s":{"a":0,"k":[100,100]},"r":{"a":0,"k":0},"o":{"a":0,"k":100},"sk":{"a":0,"k":0},"sa":{"a":0,"k":0}},"shapes":[{"ty":"sh","ks":{"a":0,"k":{"v":[[481.962,226.854],[481.525,226.701],[456.531,190.673],[456.978,189.792],[457.858,190.239],[482.07,225.346],[529.159,177.912],[530.112,177.657],[530.367,178.61],[482.232,226.801],[481.962,226.854]],"i":[[0,0],[0.126,0.1],[0.071,0.216],[-0.366,0.122],[-0.12,-0.367],[-17.133,-13.954],[-19.592,33.924],[-0.333,-0.192],[0.193,-0.335],[0.266,-0.11],[0.091,0]],"o":[[-0.156,0],[-17.702,-14.218],[-0.12,-0.366],[0.365,-0.12],[0.068,0.211],[3.287,-1.51],[0.193,-0.332],[0.334,0.192],[-21.211,36.729],[-0.088,0.035],[0,0]],"c":false}},"hd":false,"bm":0,"ln":""},{"ty":"fl","o":{"a":0,"k":100},"c":{"a":0,"k":[0.145098,0.160784,0.168627]},"hd":false,"bm":0,"ln":"","r":1}],"hd":false,"bm":0,"ln":"","ao":0,"hasMask":false,"tt":0,"td":0},{"ty":4,"st":0,"ip":0,"op":300,"ks":{"a":{"a":0,"k":[490.608505,306.44899]},"p":{"a":0,"k":[490.608505,308.44899]},"s":{"a":0,"k":[100,100]},"r":{"a":0,"k":0},"o":{"a":0,"k":100},"sk":{"a":0,"k":0},"sa":{"a":0,"k":0}},"shapes":[{"ty":"sh","ks":{"a":0,"k":{"v":[[457.195,190.455],[451.455,434.637],[510.664,434.637],[529.762,178.261],[457.195,190.455]],"i":[[0,0],[0,0],[0,0],[0,0],[0,0]],"o":[[0,0],[0,0],[0,0],[0,0],[0,0]],"c":false}},"hd":false,"bm":0,"ln":""},{"ty":"fl","o":{"a":0,"k":100},"c":{"a":0,"k":[0.94902,0.913725,0.854902]},"hd":false,"bm":0,"ln":"","r":1}],"hd":false,"bm":0,"ln":"","ao":0,"hasMask":false,"tt":0,"td":0},{"ty":4,"st":0,"ip":0,"op":300,"ks":{"a":{"a":0,"k":[474.23465,303.902496]},"p":{"a":0,"k":[474.23465,306.902496]},"s":{"a":0,"k":[100,100]},"r":{"a":0,"k":0},"o":{"a":0,"k":100},"sk":{"a":0,"k":0},"sa":{"a":0,"k":0}},"shapes":[{"ty":"sh","ks":{"a":0,"k":{"v":[[644.563,434.637],[261.847,434.637],[261.847,394.496],[363.658,365.977],[381.727,248.065],[425.021,195.813],[458.828,183.884],[457.195,190.455],[486.37,208.97],[509.322,199.245],[529.762,178.261],[528.52,173.168],[616.309,176.475],[674.519,236.875],[686.49,389.277],[644.563,434.637]],"i":[[0,0],[0,0],[0,0],[0,0],[0,0],[-22.966,8.092],[0,0],[0,0],[-11.86,0],[-6.418,6.586],[0,0],[0,0],[0,0],[-2.47,-31.463],[0,0],[24.528,0]],"o":[[0,0],[0,0],[0,0],[0,0],[3.683,-24.068],[0,0],[0,0],[5.623,12.013],[8.232,0],[0,0],[0,0],[0,0],[31.351,3.627],[0,0],[1.925,24.459],[0,0]],"c":false}},"hd":false,"bm":0,"ln":""},{"ty":"fl","o":{"a":0,"k":100},"c":{"a":0,"k":[0.058824,0.298039,0.458824]},"hd":false,"bm":0,"ln":"","r":1}],"hd":false,"bm":0,"ln":"","ao":0,"hasMask":false,"tt":0,"td":0},{"ty":4,"st":0,"ip":0,"op":300,"ks":{"a":{"a":0,"k":[435.512909,104.43166]},"p":{"a":0,"k":[435.512909,104.43166]},"s":{"a":0,"k":[100,100]},"r":{"a":0,"k":0},"o":{"a":0,"k":100},"sk":{"a":0,"k":0},"sa":{"a":0,"k":0}},"shapes":[{"ty":"sh","ks":{"a":0,"k":{"v":[[433.112,106.084],[431.727,104.836],[432.966,103.3],[437.763,102.787],[439.299,104.026],[438.06,105.562],[433.263,106.075],[433.112,106.084]],"i":[[0,0],[0.077,0.716],[-0.766,0.082],[0,0],[-0.083,-0.765],[0.766,-0.083],[0,0],[0.049,0]],"o":[[-0.704,0],[-0.083,-0.766],[0,0],[0.787,-0.08],[0.082,0.766],[0,0],[-0.052,0.006],[0,0]],"c":false}},"hd":false,"bm":0,"ln":""},{"ty":"fl","o":{"a":0,"k":100},"c":{"a":0,"k":[0.058824,0.298039,0.458824]},"hd":false,"bm":0,"ln":"","r":1}],"hd":false,"bm":0,"ln":"","ao":0,"hasMask":false,"tt":0,"td":0},{"ty":4,"st":0,"ip":0,"op":300,"ks":{"a":{"a":0,"k":[494.471664,86.970558]},"p":{"a":0,"k":[494.471664,87.970558]},"s":{"a":0,"k":[100,100]},"r":{"a":0,"k":0},"o":{"a":0,"k":100},"sk":{"a":0,"k":0},"sa":{"a":0,"k":0}},"shapes":[{"ty":"sh","ks":{"a":0,"k":{"v":[[484.4,90.3869],[483.034,89.2651],[484.128,87.623],[504.267,83.5823],[505.909,84.6762],[504.815,86.3184],[484.676,90.359],[484.4,90.3869]],"i":[[0,0],[0.133,0.6642],[-0.756,0.152],[0,0],[-0.153,-0.7562],[0.757,-0.1521],[0,0],[0.092,0]],"o":[[-0.651,0],[-0.15,-0.7548],[0,0],[0.753,-0.1535],[0.151,0.7548],[0,0],[-0.093,0.021],[0,0]],"c":false}},"hd":false,"bm":0,"ln":""},{"ty":"fl","o":{"a":0,"k":100},"c":{"a":0,"k":[0.058824,0.298039,0.458824]},"hd":false,"bm":0,"ln":"","r":1}],"hd":false,"bm":0,"ln":"","ao":0,"hasMask":false,"tt":0,"td":0},{"ty":4,"st":0,"ip":0,"op":300,"ks":{"a":{"a":0,"k":[461.570007,96.841503]},"p":{"a":0,"k":[461.570007,97.841503]},"s":{"a":0,"k":[100,100]},"r":{"a":0,"k":0},"o":{"a":0,"k":100},"sk":{"a":0,"k":0},"sa":{"a":0,"k":0}},"shapes":[{"ty":"sh","ks":{"a":0,"k":{"v":[[461.571,128.102],[436.515,96.8414],[461.571,65.581],[486.625,96.8414],[461.571,128.102],[461.571,68.3701],[439.306,96.84],[461.571,125.31],[483.835,96.84],[461.571,68.3701]],"i":[[0,0],[0,17.2366],[-13.816,0],[0,-17.2368],[13.814,0],[0,0],[0,-15.6993],[-12.277,0],[0,15.699],[12.277,0]],"o":[[-13.816,0],[0,-17.2368],[13.814,0],[0,17.2366],[0,0],[-12.277,0],[0,15.699],[12.277,0],[0,-15.6993],[0,0]],"c":false}},"hd":false,"bm":0,"ln":""},{"ty":"fl","o":{"a":0,"k":100},"c":{"a":0,"k":[0.058824,0.298039,0.458824]},"hd":false,"bm":0,"ln":"","r":1}],"hd":false,"bm":0,"ln":"","ao":0,"hasMask":false,"tt":0,"td":0},{"ty":4,"st":0,"ip":0,"op":300,"ks":{"a":{"a":0,"k":[409.625,108.246799]},"p":{"a":0,"k":[409.625,108.246799]},"s":{"a":0,"k":[100,100]},"r":{"a":0,"k":0},"o":{"a":0,"k":100},"sk":{"a":0,"k":0},"sa":{"a":0,"k":0}},"shapes":[{"ty":"sh","ks":{"a":0,"k":{"v":[[409.626,139.508],[384.57,108.247],[409.626,76.9856],[434.68,108.247],[409.626,139.508],[409.626,79.7747],[387.361,108.246],[409.626,136.716],[431.89,108.246],[409.626,79.7747]],"i":[[0,0],[0,17.237],[-13.816,0],[0,-17.2364],[13.814,0],[0,0],[0,-15.6992],[-12.277,0],[0,15.699],[12.275,0]],"o":[[-13.816,0],[0,-17.2364],[13.814,0],[0,17.237],[0,0],[-12.277,0],[0,15.699],[12.277,0],[0,-15.6992],[0,0]],"c":false}},"hd":false,"bm":0,"ln":""},{"ty":"fl","o":{"a":0,"k":100},"c":{"a":0,"k":[0.058824,0.298039,0.458824]},"hd":false,"bm":0,"ln":"","r":1}],"hd":false,"bm":0,"ln":"","ao":0,"hasMask":false,"tt":0,"td":0},{"ty":4,"st":0,"ip":0,"op":300,"ks":{"a":{"a":0,"k":[442.527145,121.8125]},"p":{"a":0,"k":[442.527145,122.8125]},"s":{"a":0,"k":[100,100]},"r":{"a":0,"k":0},"o":{"a":0,"k":100},"sk":{"a":0,"k":0},"sa":{"a":0,"k":0}},"shapes":[{"ty":"sh","ks":{"a":0,"k":{"v":[[435.827,137.733],[435.449,137.623],[435.13,137.04],[434.947,106.594],[435.64,105.892],[435.645,105.892],[436.342,106.586],[436.518,135.963],[449.125,130.312],[450.046,130.663],[449.695,131.584],[436.112,137.672],[435.827,137.733]],"i":[[0,0],[0.116,0.074],[0,0.235],[0,0],[-0.385,0.003],[0,0],[-0.003,-0.384],[0,0],[0,0],[-0.157,-0.351],[0.351,-0.156],[0,0],[0.097,0]],"o":[[-0.132,0],[-0.199,-0.129],[0,0],[-0.003,-0.385],[0,0],[0.382,0],[0,0],[0,0],[0.349,-0.162],[0.158,0.352],[0,0],[-0.089,0.04],[0,0]],"c":false}},"hd":false,"bm":0,"ln":""},{"ty":"fl","o":{"a":0,"k":100},"c":{"a":0,"k":[0.145098,0.160784,0.168627]},"hd":false,"bm":0,"ln":"","r":1}],"hd":false,"bm":0,"ln":"","ao":0,"hasMask":false,"tt":0,"td":0},{"ty":4,"st":0,"ip":0,"op":300,"ks":{"a":{"a":0,"k":[456.512939,139.473]},"p":{"a":0,"k":[456.512939,140.473]},"s":{"a":0,"k":[100,100]},"r":{"a":0,"k":0},"o":{"a":0,"k":100},"sk":{"a":0,"k":0},"sa":{"a":0,"k":0}},"shapes":[{"ty":"sh","ks":{"a":0,"k":{"v":[[451.454,145.969],[450.761,145.336],[451.391,144.577],[458.303,141.039],[460.864,133.705],[461.529,132.978],[461.56,132.977],[462.256,133.644],[459.355,141.955],[451.52,145.968],[451.454,145.969]],"i":[[0,0],[0.033,0.363],[-0.383,0.035],[-1.745,2.002],[0.118,2.655],[-0.385,0.016],[-0.009,0],[-0.017,-0.376],[1.979,-2.271],[2.999,-0.279],[0.022,0]],"o":[[-0.356,0],[-0.035,-0.382],[2.646,-0.246],[1.746,-2.005],[-0.019,-0.385],[0.011,-0.001],[0.372,0],[0.137,3.009],[-1.98,2.272],[-0.023,0],[0,0]],"c":false}},"hd":false,"bm":0,"ln":""},{"ty":"fl","o":{"a":0,"k":100},"c":{"a":0,"k":[0.145098,0.160784,0.168627]},"hd":false,"bm":0,"ln":"","r":1}],"hd":false,"bm":0,"ln":"","ao":0,"hasMask":false,"tt":0,"td":0},{"ty":4,"st":0,"ip":0,"op":300,"ks":{"a":{"a":0,"k":[464.856232,167.857391]},"p":{"a":0,"k":[464.856232,171.857391]},"s":{"a":0,"k":[100,100]},"r":{"a":0,"k":0},"o":{"a":0,"k":100},"sk":{"a":0,"k":0},"sa":{"a":0,"k":0}},"shapes":[{"ty":"sh","ks":{"a":0,"k":{"v":[[460.543,175.129],[459.704,175.108],[446.594,170.381],[446.336,169.428],[447.289,169.17],[459.772,173.714],[472.2,169.809],[482.268,160.799],[483.254,160.78],[483.274,161.766],[472.972,170.972],[460.543,175.129]],"i":[[0,0],[0.282,0.014],[4.038,2.32],[-0.191,0.334],[-0.332,-0.19],[-4.148,-0.204],[-2.891,1.918],[-2.916,3.027],[-0.274,-0.264],[0.267,-0.276],[3.973,-2.637],[5.066,0]],"o":[[-0.278,0],[-4.688,-0.229],[-0.333,-0.193],[0.193,-0.337],[4.493,2.581],[4.997,0.234],[3.847,-2.552],[0.269,-0.279],[0.278,0.266],[-2.966,3.08],[-2.907,1.928],[0,0]],"c":false}},"hd":false,"bm":0,"ln":""},{"ty":"fl","o":{"a":0,"k":100},"c":{"a":0,"k":[0.145098,0.160784,0.168627]},"hd":false,"bm":0,"ln":"","r":1}],"hd":false,"bm":0,"ln":"","ao":0,"hasMask":false,"tt":0,"td":0},{"ty":4,"st":0,"ip":0,"op":300,"ks":{"a":{"a":0,"k":[525.946259,102.423504]},"p":{"a":0,"k":[525.946259,103.423504]},"s":{"a":0,"k":[100,100]},"r":{"a":0,"k":0},"o":{"a":0,"k":100},"sk":{"a":0,"k":0},"sa":{"a":0,"k":0}},"shapes":[{"ty":"sh","ks":{"a":0,"k":{"v":[[521.458,121.903],[520.761,121.24],[521.423,120.509],[531.305,113.45],[529.052,101.517],[523.769,98.8519],[519.139,101.616],[518.391,102.054],[517.794,101.423],[518.219,92.1184],[523.432,84.2646],[528.961,83.1303],[534.179,87.9787],[533.966,88.9414],[533.003,88.728],[528.598,84.4767],[524.196,85.4338],[519.574,92.4575],[519.042,99.2844],[523.82,97.4552],[530.069,100.56],[532.6,113.969],[521.494,121.9],[521.458,121.903]],"i":[[0,0],[0.02,0.374],[-0.387,0.018],[-1.582,3.939],[2.909,3.089],[1.824,0.0641],[0.648,-1.6731],[0.318,0.042],[0.029,0.324],[-0.808,3.2258],[-2.5,1.6352],[-1.702,-0.4647],[-1.343,-2.104],[0.325,-0.2079],[0.209,0.3251],[1.887,0.5092],[1.475,-0.9641],[0.776,-3.0877],[-0.104,-2.1738],[-1.842,-0.0614],[-1.808,-1.923],[1.807,-4.494],[4.837,-0.248],[0.011,0]],"o":[[-0.37,0],[-0.021,-0.384],[4.237,-0.218],[1.582,-3.938],[-1.534,-1.6299],[-2.074,-0.1256],[-0.118,0.303],[-0.321,-0.046],[-0.245,-2.7902],[0.861,-3.4295],[1.811,-1.1846],[2.367,0.6376],[0.207,0.3237],[-0.321,0.2051],[-1.244,-1.9492],[-1.325,-0.3544],[-2.204,1.4413],[-0.575,2.2937],[1.189,-1.1888],[2.221,0.0796],[3.321,3.525],[-1.805,4.496],[-0.013,0.003],[0,0]],"c":false}},"hd":false,"bm":0,"ln":""},{"ty":"fl","o":{"a":0,"k":100},"c":{"a":0,"k":[0.145098,0.160784,0.168627]},"hd":false,"bm":0,"ln":"","r":1}],"hd":false,"bm":0,"ln":"","ao":0,"hasMask":false,"tt":0,"td":0},{"ty":4,"st":0,"ip":0,"op":300,"ks":{"a":{"a":0,"k":[457.314682,91.919949]},"p":{"a":0,"k":[457.314682,92.919949]},"s":{"a":0,"k":[100,100]},"r":{"a":0,"k":0},"o":{"a":0,"k":100},"sk":{"a":0,"k":0},"sa":{"a":0,"k":0}},"shapes":[{"ty":"sh","ks":{"a":0,"k":{"v":[[449.323,94.1067],[452.132,94.4583],[452.196,94.4192],[452.255,94.3899],[452.598,94.2113],[453.3,93.8862],[454.757,93.3658],[454.791,93.3546],[454.798,93.3532],[455.175,93.2667],[455.937,93.1258],[457.479,92.9765],[457.901,92.9667],[458.026,92.9709],[458.799,93.0226],[460.328,93.2583],[460.704,93.3449],[460.787,93.3658],[461.507,93.6002],[462.928,94.2127],[465.543,93.1314],[464.462,90.5167],[449.674,91.2994],[449.323,94.1067]],"i":[[0,0],[-0.893,0.5371],[-0.022,0.0139],[-0.031,0.0153],[-0.116,0.0572],[-0.237,0.1019],[-0.494,0.1507],[-0.015,0.0042],[-0.005,0.0014],[-0.125,0.0265],[-0.255,0.0405],[-0.517,0.0195],[-0.141,0.0014],[-0.046,-0.0014],[-0.257,-0.0252],[-0.504,-0.1088],[-0.125,-0.0293],[-0.027,-0.007],[-0.237,-0.0851],[-0.463,-0.2302],[-0.431,0.9278],[0.936,0.466],[4.452,-2.6844],[-0.565,-0.7981]],"o":[[0.676,0.9529],[0.029,-0.0182],[0.013,-0.0056],[0.114,-0.06],[0.23,-0.1158],[0.476,-0.2023],[0.027,-0.0084],[0.006,-0.0014],[0.126,-0.0307],[0.253,-0.0544],[0.511,-0.0795],[0.141,-0.0056],[0.034,0.0014],[0.258,0.0126],[0.513,0.0488],[0.125,0.0266],[0.027,0.0069],[0.241,0.0725],[0.487,0.1744],[1.001,0.4981],[0.479,-1.0255],[-4.709,-2.3468],[-0.959,0.5763],[0,0]],"c":false}},"hd":false,"bm":0,"ln":""},{"ty":"fl","o":{"a":0,"k":100},"c":{"a":0,"k":[0.145098,0.160784,0.168627]},"hd":false,"bm":0,"ln":"","r":1}],"hd":false,"bm":0,"ln":"","ao":0,"hasMask":false,"tt":0,"td":0},{"ty":4,"st":0,"ip":0,"op":300,"ks":{"a":{"a":0,"k":[415.410233,102.635494]},"p":{"a":0,"k":[415.410233,103.635494]},"s":{"a":0,"k":[100,100]},"r":{"a":0,"k":0},"o":{"a":0,"k":100},"sk":{"a":0,"k":0},"sa":{"a":0,"k":0}},"shapes":[{"ty":"sh","ks":{"a":0,"k":{"v":[[421.608,98.0147],[408.068,104.013],[408.288,106.834],[411.109,106.614],[412.098,105.423],[412.634,104.888],[412.698,104.832],[412.996,104.584],[414.253,103.681],[414.918,103.285],[415.027,103.225],[415.408,103.042],[416.851,102.478],[417.593,102.259],[417.968,102.166],[417.975,102.164],[418.011,102.159],[419.546,101.963],[420.319,101.935],[420.706,101.94],[420.771,101.94],[420.847,101.945],[423.192,100.36],[421.608,98.0147]],"i":[[0,0],[3.137,-4.2249],[-0.892,-0.698],[-0.667,0.897],[-0.354,0.377],[-0.183,0.174],[-0.022,0.018],[-0.101,0.082],[-0.436,0.276],[-0.224,0.128],[-0.031,0.015],[-0.127,0.058],[-0.492,0.161],[-0.25,0.066],[-0.125,0.029],[-0.005,0.002],[-0.029,0.005],[-0.516,0.035],[-0.258,0.002],[-0.129,-0.003],[-0.014,0],[-0.035,-0.003],[-0.17,1.155],[1.117,0.0809]],"o":[[-5.184,-0.3781],[-0.624,0.84],[0.805,0.631],[0.308,-0.415],[0.173,-0.184],[0.02,-0.018],[0.098,-0.084],[0.4,-0.326],[0.217,-0.138],[0.041,-0.023],[0.126,-0.063],[0.47,-0.215],[0.245,-0.081],[0.124,-0.033],[0.007,-0.002],[0.015,-0.003],[0.51,-0.09],[0.258,-0.016],[0.129,-0.001],[0.035,0],[0.025,0.001],[1.039,0.075],[0.144,-0.9682],[0,0]],"c":false}},"hd":false,"bm":0,"ln":""},{"ty":"fl","o":{"a":0,"k":100},"c":{"a":0,"k":[0.145098,0.160784,0.168627]},"hd":false,"bm":0,"ln":"","r":1}],"hd":false,"bm":0,"ln":"","ao":0,"hasMask":false,"tt":0,"td":0},{"ty":4,"st":0,"ip":0,"op":300,"ks":{"a":{"a":0,"k":[458.794998,106.452888]},"p":{"a":0,"k":[458.794998,107.452888]},"s":{"a":1,"k":[{"t":120,"s":[100,100],"i":{"x":1,"y":1},"o":{"x":0,"y":0},"h":0},{"t":150,"s":[100,7.8133],"i":{"x":1,"y":1},"o":{"x":0,"y":0},"h":0},{"t":180,"s":[100,100],"i":{"x":1,"y":1},"o":{"x":0,"y":0},"h":0}]},"r":{"a":0,"k":-12.846826},"o":{"a":0,"k":100},"sk":{"a":0,"k":0},"sa":{"a":0,"k":0}},"shapes":[{"ty":"sh","ks":{"a":0,"k":{"v":[[460.473,113.468],[465.137,104.935],[457.116,99.4378],[452.453,107.97],[460.473,113.468]],"i":[[0,0],[0.927,3.875],[3.503,-0.8381],[-0.927,-3.874],[-3.502,0.838]],"o":[[3.503,-0.838],[-0.927,-3.874],[-3.502,0.8382],[0.927,3.875],[0,0]],"c":false}},"hd":false,"bm":0,"ln":""},{"ty":"fl","o":{"a":0,"k":100},"c":{"a":0,"k":[0.145098,0.160784,0.168627]},"hd":false,"bm":0,"ln":"","r":1}],"hd":false,"bm":0,"ln":"","ao":0,"hasMask":false,"tt":0,"td":0},{"ty":4,"st":0,"ip":0,"op":300,"ks":{"a":{"a":0,"k":[420.243973,115.676003]},"p":{"a":0,"k":[420.243973,116.676003]},"s":{"a":1,"k":[{"t":120,"s":[100,100],"i":{"x":1,"y":1},"o":{"x":0,"y":0},"h":0},{"t":150,"s":[85.2026,6.5672],"i":{"x":1,"y":1},"o":{"x":0,"y":0},"h":0},{"t":180,"s":[100,100],"i":{"x":1,"y":1},"o":{"x":0,"y":0},"h":0}]},"r":{"a":0,"k":-12.786349},"o":{"a":0,"k":100},"sk":{"a":0,"k":0},"sa":{"a":0,"k":0}},"shapes":[{"ty":"sh","ks":{"a":0,"k":{"v":[[421.922,122.691],[426.586,114.159],[418.565,108.661],[413.902,117.194],[421.922,122.691]],"i":[[0,0],[0.927,3.874],[3.503,-0.838],[-0.927,-3.875],[-3.502,0.838]],"o":[[3.503,-0.838],[-0.927,-3.875],[-3.503,0.838],[0.927,3.874],[0,0]],"c":false}},"hd":false,"bm":0,"ln":""},{"ty":"fl","o":{"a":0,"k":100},"c":{"a":0,"k":[0.145098,0.160784,0.168627]},"hd":false,"bm":0,"ln":"","r":1}],"hd":false,"bm":0,"ln":"","ao":0,"hasMask":false,"tt":0,"td":0},{"ty":4,"st":0,"ip":0,"op":300,"ks":{"a":{"a":0,"k":[475.831589,129.929497]},"p":{"a":0,"k":[475.831589,133.976997]},"s":{"a":0,"k":[100,100]},"r":{"a":0,"k":0},"o":{"a":0,"k":100},"sk":{"a":0,"k":0},"sa":{"a":0,"k":0}},"shapes":[{"ty":"sh","ks":{"a":0,"k":{"v":[[541.189,109.126],[517.665,128.409],[528.52,173.168],[529.762,178.261],[509.322,199.245],[486.37,208.97],[457.196,190.455],[458.828,183.884],[461.186,174.438],[459.219,173.824],[438.067,163.178],[418.645,141.203],[410.678,112.963],[409.157,83.3703],[414.934,69.9341],[437.578,50.889],[447.778,63.2788],[504.536,84.9469],[504.662,84.9609],[504.662,85.1283],[504.718,85.0864],[519.423,77.1614],[528.227,77.6637],[541.189,109.126]],"i":[[0,0],[12.013,1.688],[0,0],[0,0],[0,0],[8.232,0],[5.622,12.013],[0,0],[0,0],[0,0],[6.432,4.646],[4.688,8.567],[0.516,10.046],[0,0],[-2.54,3.8369],[0,0],[-3.754,-3.544],[-2.162,-0.0279],[0,0],[0,0],[0,0.014],[-5.553,0.7953],[-2.944,-0.7534],[3.642,-13.8822]],"o":[[-3.376,12.92],[0,0],[0,0],[0,0],[-6.418,6.586],[-11.859,0],[0,0],[0,0],[0,0],[-7.563,-2.414],[-8.148,-5.874],[-4.674,-8.581],[0,0],[1.172,-5.1345],[8.706,-13.2688],[2.972,4.7717],[22.156,20.7472],[0,0],[0,0],[0.028,0],[3.962,-4.3113],[2.875,-0.4046],[12.823,3.3765],[0,0]],"c":false}},"hd":false,"bm":0,"ln":""},{"ty":"fl","o":{"a":0,"k":100},"c":{"a":0,"k":[0.94902,0.913725,0.854902]},"hd":false,"bm":0,"ln":"","r":1}],"hd":false,"bm":0,"ln":"","ao":0,"hasMask":false,"tt":0,"td":0},{"ty":4,"st":0,"ip":0,"op":300,"ks":{"a":{"a":0,"k":[508.272354,122.990025]},"p":{"a":0,"k":[508.272354,123.990025]},"s":{"a":0,"k":[100,100]},"r":{"a":0,"k":0},"o":{"a":0,"k":100},"sk":{"a":0,"k":0},"sa":{"a":0,"k":0}},"shapes":[{"ty":"sh","ks":{"a":0,"k":{"v":[[639.038,176.628],[563.248,216.238],[517.568,245.902],[467.422,230.024],[407.092,238.968],[385.243,216.714],[396.474,188.683],[393.533,107.522],[390.348,76.7847],[400.83,34.453],[446.677,9.64413],[541.093,44.9313],[557.907,83.9674],[595.086,130.221],[639.038,176.628]],"i":[[0,0],[23.408,-16.026],[19.403,-1.597],[18.715,-1.406],[20.618,5.49],[1.437,11.259],[-4.674,8.986],[-43.24,53.787],[9.052,8.3924],[-22.529,3.6597],[-15.167,8.50957],[-10.191,-39.82729],[-19.326,-9.0761],[-9.451,-31.5715],[-1.054,-25.205]],"o":[[-3.169,39.398],[-14.709,10.418],[-18.709,1.43],[-20.32,0.786],[-10.408,-2.874],[-1.396,-10.953],[13.25,-32.784],[7.761,-10.0207],[-11.713,-14.8524],[16.994,-4.8136],[33.89,-22.08253],[4.843,15.8123],[35.736,11.6656],[11.419,18.196],[0,0]],"c":false}},"hd":false,"bm":0,"ln":""},{"ty":"fl","o":{"a":0,"k":100},"c":{"a":0,"k":[0.145098,0.160784,0.168627]},"hd":false,"bm":0,"ln":"","r":1}],"hd":false,"bm":0,"ln":"","ao":0,"hasMask":false,"tt":0,"td":0}]}